{
  "fluentMethods": true,
  "clientRootFolder": "",
  "relationships": [],
  "fields": [
    {
      "fieldName": "supplierId",
      "fieldType": "Long"
    },
    {
      "fieldName": "totalAmount",
      "fieldType": "Double"
    },
    {
      "fieldName": "paymentType",
      "fieldType": "PaymentType",
      "fieldValues": "CREDIT,CASH,PARTIAL"
    },
    {
      "fieldName": "orderStatus",
      "fieldType": "OrderStatus",
      "fieldValues": "COMPLETED,INPROGRESS,FAILED,CANCELLED,DELIVERED,PAYMENT_DUE,REFUNDED"
    },
    {
      "fieldName": "paymentStatus",
      "fieldType": "PaymentStatus",
      "fieldValues": "PAID,UNPAID,PARTIAL_PAID,REFUNDED,PARTIAL_REFUNDED"
    },
    {
      "fieldName": "shippingDate",
      "fieldType": "LocalDate"
    },
    {
      "fieldName": "shippingRequired",
      "fieldType": "Boolean",
      "fieldValidateRules": ["required"]
    },
    {
      "fieldName": "createdDate",
      "fieldType": "LocalDate"
    },
    {
      "fieldName": "createdBy",
      "fieldType": "String"
    },
    {
      "fieldName": "remarks",
      "fieldType": "String"
    }
  ],
  "changelogDate": "20210422222118",
  "dto": "no",
  "searchEngine": false,
  "service": "serviceClass",
  "entityTableName": "purchase_order",
  "databaseType": "sql",
  "readOnly": false,
  "jpaMetamodelFiltering": false,
  "pagination": "pagination"
}
